audioplayerx/__init__.py
audioplayerx/player.py
audioplayerx-0.1.dist-info/METADATA
audioplayerx-0.1.dist-info/WHEEL
audioplayerx-0.1.dist-info/top_level.txt
audioplayerx-0.1.dist-info/RECORD
