Metadata-Version: 2.1
Name: audioplayerx
Version: 0.1
Summary: mp3 ve wav calabilen sade kutuphane
Home-page: https://github.com/ruzgar/audioplayerx
Author: Ruzgar
Classifier: Programming Language :: Python :: 3
Classifier: Operating System :: OS Independent
Requires-Python: >=3.6
Requires-Dist: playsound ; platform_system == "Windows"
